LoadPredConverge.py
LoadPredConverge-0.0.1.dist-info/LICENSE.txt
LoadPredConverge-0.0.1.dist-info/METADATA
LoadPredConverge-0.0.1.dist-info/WHEEL
LoadPredConverge-0.0.1.dist-info/top_level.txt
LoadPredConverge-0.0.1.dist-info/RECORD
