Metadata-Version: 2.1
Name: LoadPredConverge
Version: 0.0.1
Summary: Residential electricity forecasting and disaggregation module
License: UNKNOWN
Platform: UNKNOWN
License-File: LICENSE.txt
Requires-Dist: skforecast (==0.4.2)
Requires-Dist: sklearn
Requires-Dist: more-itertools
Requires-Dist: multiprocess
Requires-Dist: pyomo
